{"id":"12-hard-1018","theme":"beach","grid":"FLLABDNAHZODLLABYELLOVKDHCALIFORNIAEGWPAYPSWDNNSRZUNOYBKAOAULRZDBHGOYIEOADZIEAUMTSCHTNLNARZCOOOTSAEGCBRCNRSHALGZHOPVAEGGONNVEUDUNESICILNSRWEEXQL","solution":"65;1;7,126;0;5,12;0;10,64;1;7,27;1;7,143;5;10,73;1;6,8;4;8,44;1;7,25;0;10,38;1;6,132;5;7,94;5;5,45;1;7","gridSize":12,"difficulty":"hard","wordCount":14,"wordlist":["DUNES","OCEAN","INLAND","PUZZLE","BEACHES","COASTAL","DAYTONA","EROSION","HARBOUR","LANDING","HANDBALL","CALIFORNIA","LIGHTHOUSE","VOLLEYBALL"]}