{"id":"12-hard-1081","theme":"beach","grid":"QRCVSOCCERWDJUEVANTVNVZZBOULEVARDFOYVFLNSYOBBMSCELSZOGNIDNALLOTEXTOURISTZRIAHDMUJTRFZIXYFCLPIERAUDNOITAERCERPAZXLFPEQKRUFELZZUPYBFREXHESUOHTHGIL","solution":"9;4;6,65;0;7,94;4;4,128;6;7,114;5;4,143;4;10,24;0;9,8;2;4,98;0;10,40;0;4,59;4;7,37;1;7,108;5;6,126;4;6","gridSize":12,"difficulty":"hard","wordCount":14,"wordlist":["BOYS","COVE","PALM","PIER","PUZZLE","PUZZLE","SOCCER","BEACHES","FLORIDA","LANDING","TOURIST","BOULEVARD","LIGHTHOUSE","RECREATION"]}