{"id":"12-hard-1162","theme":"beach","grid":"ZTXXSKGIFDYELDOSGPDNIRRRKICUKGJLSAMUCAGURVTAHVKOOLAHDINNIEABVJHUTESDNLDREPNYWHETGUIACEXPKROUWORHSBOELZZUPBOMTRRECCOSSPLHTTIDEMVEYEFVAREIPORAAXFK","solution":"120;3;7,129;6;10,1;2;7,23;1;7,72;5;4,124;4;4,136;4;4,105;5;9,130;5;7,115;4;6,52;7;5,8;1;7,7;1;6,104;4;6","gridSize":12,"difficulty":"hard","wordCount":14,"wordlist":["COVE","PIER","TIDE","DUNES","INLAND","PUZZLE","SOCCER","FISHING","FLORIDA","HARBOUR","NEWPORT","TOURIST","BOULEVARD","LIGHTHOUSE"]}