{"id":"12-hard-1743","theme":"beach","grid":"KIHANDBALLERVEKBOYSBRQHEWRUDOMVOVZMCYOUNLSOUZCGRTHLAPYLLTHNEPSPLUELEROIAIEENZQEVOTDTCILIZNYAPENINXMTLDBRWLAOIATAEVADESLNCPVYIELXNCYLWEEGSMLPARWK","solution":"11;1;10,29;7;4,138;5;10,2;0;8,85;2;5,128;5;7,19;1;9,57;1;6,46;1;7,15;0;4,87;5;6,61;5;5,60;1;6,52;1;6","gridSize":12,"difficulty":"hard","wordCount":14,"wordlist":["BOYS","PALM","MIAMI","SHORE","HOTELS","INLAND","PICNIC","PUZZLE","LANDING","NEWPORT","HANDBALL","BOULEVARD","RECREATION","VOLLEYBALL"]}