{"id":"12-hard-1990","theme":"beach","grid":"UBOULEVARDGVXGFTQMIAMIUIMESUOHTHGILEAKHSYOBEAGRSYERHGRLDNOENGVUOOZIISZTODYYBZRDISDSCMWRUONOEQOIEBAPLANNZFWRAHQFLXUKBUBUNPLSMDYCRZAOFDNEWPORTOYTG","solution":"101;3;7,108;3;6,133;0;7,17;0;5,111;3;7,110;3;7,1;0;9,39;0;4,124;3;5,142;5;7,25;0;10,98;3;6,141;5;3,71;1;5","gridSize":12,"difficulty":"hard","wordCount":14,"wordlist":["BAY","BOYS","DUNES","MIAMI","OCEAN","HARBOR","PUZZLE","EROSION","FLORIDA","LANDING","NEWPORT","TOURIST","BOULEVARD","LIGHTHOUSE"]}