{"id":"12-hard-2178","theme":"beach","grid":"WRUOBRAHBJALTTFDNALNINILASSCLIFFSPNANHICOVEDZBRBOEYRYTJCOEOYTFLMUDJUJNFEYPTZTOLGOTILAFIFZETIVULLDZIEVUSVIEAONEUAROPSETCVBMRSRCINCIPXZDWEBSLETOHO","solution":"32;4;6,69;7;7,20;4;6,90;6;7,39;0;4,45;7;9,7;4;7,118;5;10,112;6;4,130;4;6,11;1;10,114;6;6,24;1;7,142;4;6","gridSize":12,"difficulty":"hard","wordCount":14,"wordlist":["COVE","PIER","CLIFFS","HOTELS","INLAND","PICNIC","PUZZLE","DAYTONA","EROSION","HARBOUR","TOURIST","BOULEVARD","CALIFORNIA","VOLLEYBALL"]}