{"id":"12-hard-243","theme":"beach","grid":"TRSLLABDNAHGFVFFUTDOCEANRTKHFNBEQSEGETTAAIDXYUSNCARLDRLTLOEIRLNOEIBCLTHHEIQEPEROIFCSAFKHBWROUGAITVIIXAEOLREFIBDWWLYNHFBDOGNIMMIWSSOCNNRSEVAWYCPA","solution":"46;1;7,117;6;7,115;6;7,24;1;10,19;0;5,67;6;6,77;2;5,139;4;5,107;5;7,27;2;7,10;4;8,128;4;8,88;2;3,18;7;6","gridSize":12,"difficulty":"hard","wordCount":14,"wordlist":["BAY","OCEAN","SHORE","WAVES","CLIFFS","INLAND","BEACHES","FISHING","FLORIDA","HARBOUR","NEWPORT","HANDBALL","SWIMMING","RECREATION"]}