{"id":"12-hard-2547","theme":"beach","grid":"HFCDAYTONAWBFHCDSHARBORELVARJBPYUBTAOOLEVOBAWWSCRLICNUKBTQIHILFRELRLFOREDEOEWELAKTUSAYRAPVUTKUOPLBNTOAGSTJTANAIIRRNAECOLLLAOTDZOCBEMHLZNWOICBMUI","solution":"135;5;10,55;5;3,83;5;7,124;5;7,139;5;7,12;1;7,114;0;5,17;0;6,25;1;10,95;1;4,125;5;9,106;5;7,3;0;7,14;1;10","gridSize":12,"difficulty":"hard","wordCount":14,"wordlist":["BAY","PALM","OCEAN","HARBOR","BEACHES","COASTAL","DAYTONA","FLORIDA","NEWPORT","TOURIST","BOULEVARD","CALIFORNIA","RECREATION","VOLLEYBALL"]}