{"id":"12-hard-2609","theme":"beach","grid":"VBHHPHRBXMCWQORAAUMEGGIZHHLDRNZEINNNVCFLGBDZWPCTTPPIENOBLTIRDUNESYIUAEPOWZKSHHBMRLRPQZASFYIAMTLWILNEOFJNLIAEPEVVPHIZGLWNMJGAVXFLSBOSWDZWKSEHCAEB","solution":"75;2;6,64;4;5,80;6;7,40;2;8,117;6;10,45;6;4,135;5;5,3;2;8,119;5;7,4;2;6,143;4;7,49;1;6,38;2;7,70;5;6","gridSize":12,"difficulty":"hard","wordCount":14,"wordlist":["PIER","DUNES","WAVES","CLIFFS","PICNIC","PUZZLE","PUZZLE","BEACHES","FISHING","HARBOUR","NEWPORT","HANDBALL","SWIMMING","VOLLEYBALL"]}