{"id":"12-hard-2717","theme":"beach","grid":"RKQPFGXNBZEFJALWPNAEQCPNFMIAMINWIOUAHUWFWHOPOAZERGEAJSTOVSZCCOVEMIYRVTLOWETMIFATAAEJSDJVHPDOULSEPIERGNIMMIWSXOBJHOTELSNRKAINROFILACLJESUOHTHGILE","solution":"60;0;4,112;0;6,90;5;7,100;0;8,79;5;7,130;4;10,77;5;7,142;4;10,96;0;4,25;0;5,22;1;6,40;7;5,21;1;7,23;1;5","gridSize":12,"difficulty":"hard","wordCount":14,"wordlist":["COVE","PIER","MIAMI","OCEAN","WAVES","HOTELS","PUZZLE","COASTAL","DAYTONA","FISHING","NEWPORT","SWIMMING","CALIFORNIA","LIGHTHOUSE"]}