{"id":"12-hard-3006","theme":"beach","grid":"TSIRUOTIJSXKMSHARBORIHHCLHLZDDQBOROOAOXTNISTDETAPRAAOLCUDITSXELTEKXLTPVTANWTQRFKIVLAIDOIEDITMFRLDHJGYUEVOCFYNOITAERCERZSMCALIFORNIANQOVOLLEYBALL","solution":"42;7;6,84;3;6,134;0;10,61;5;5,54;2;6,33;1;4,6;4;7,130;4;10,117;4;10,88;0;4,48;5;4,14;0;6,23;1;7,105;4;4","gridSize":12,"difficulty":"hard","wordCount":14,"wordlist":["COVE","PALM","PIER","TIDE","SHORE","CLIFFS","HARBOR","HOTELS","INLAND","COASTAL","TOURIST","CALIFORNIA","RECREATION","VOLLEYBALL"]}