{"id":"12-hard-3102","theme":"beach","grid":"CVHIMPRTUGCWNFVANTIDEMSPSOTONLKUOLLLVKIPLDAUKAEAQHHTNLBNOPTTBESXAOEADTOSXKOCQNIYLTHAPKCCFYISBLEOWICEFSXTOADCGYEEVOCASRLGKBRRIMAIMEELFLBOULEVARDF","solution":"3;2;6,12;2;11,114;4;4,93;6;8,21;1;4,122;5;6,35;1;7,130;6;7,84;2;4,17;0;4,82;5;6,14;2;10,128;4;5,134;0;9","gridSize":12,"difficulty":"hard","wordCount":14,"wordlist":["COVE","PALM","PIER","TIDE","MIAMI","HOTELS","INLAND","SOCCER","COASTAL","EROSION","HANDBALL","BOULEVARD","VOLLEYBALL","DESTINATION"]}