{"id":"12-hard-3403","theme":"beach","grid":"GPBOULEVARDPHDUMZYVWGDVYNAEZBAZAINKWICNSZBEVGAZUGLEDTLQEXLGZNIQGBIESINIXIFCRNANLXIUPMFNLWALAKBIKMSYKBKELTENJILATSAOCRISRWCINCIPPOJOMSTALTEROSION","solution":"48;1;8,143;6;11,116;3;4,19;1;5,109;0;7,37;1;6,128;6;5,103;6;8,81;5;6,126;4;6,137;0;7,2;0;9,1;2;6,41;5;3","gridSize":12,"difficulty":"hard","wordCount":14,"wordlist":["BAY","PIER","OCEAN","WAVES","CLIFFS","INLAND","PICNIC","PUZZLE","COASTAL","EROSION","HANDBALL","SWIMMING","BOULEVARD","DESTINATION"]}