{"id":"12-hard-345","theme":"beach","grid":"YCTWYFLORIDAPASIUTANNXOEALODDEHCOHIRLICRPEOOIQLOMFCAIHYMTLWHGOEVEAYLAEFSNRRERRDYEULOINJLLBWWRWTSHIMUOOBZCOVESAGOJUVLEEFIIRSBXRSWRWMIFGNIMMIWSEQJ","solution":"140;4;8,40;1;4,74;5;6,107;4;4,53;1;7,95;6;6,12;1;4,11;4;7,1;1;10,2;2;4,128;5;10,123;5;9,132;5;7,23;1;5","gridSize":12,"difficulty":"hard","wordCount":14,"wordlist":["COVE","PALM","PIER","TIDE","SHORE","HOTELS","SOCCER","FISHING","FLORIDA","HARBOUR","SWIMMING","BOULEVARD","CALIFORNIA","RECREATION"]}