{"id":"12-hard-541","theme":"technology","grid":"BPJDOLOJSSJNSQHQSRDLYCNMWPCINWUAEILAYRONOISCINATJSMNIRRINOCHQOPOTEBRSRIEAFUVULSTTTNMFTTALENCICAARWITOSDETEHTTANISSQLULCINRGOICTETEECZEINWTYXETMS","solution":"124;0;3,25;3;3,49;1;8,29;1;8,26;1;9,44;1;9,112;5;9,127;5;10,27;1;10,142;5;10,129;5;11,23;1;11","gridSize":12,"difficulty":"hard","wordCount":12,"wordlist":["ICT","PHD","SOFTWARE","WIRELESS","COMPUTING","INSTITUTE","SOLUTIONS","ELECTRICAL","INNOVATION","MECHANICAL","ELECTRONICS","MATHEMATICS"]}