{"id":"12-hard-608","theme":"beach","grid":"ZGSWIMMINGGIPICNICOXPLNNNSMTSIRUOTIOOSFTSQXAOEHIIRKFUDUNESSTTDOCIKXFCSIAAPOBSLLRLZFNEABCROCEVBYIRLOIRATTVEZTCMCIIOHKOOZSEFDYHRDJWICERADAYTONAJND","solution":"67;7;7,57;4;5,69;7;6,2;0;8,12;0;6,143;5;11,132;5;10,82;5;7,73;1;4,140;4;7,25;2;6,27;0;7,130;6;4,114;6;6","gridSize":12,"difficulty":"hard","wordCount":14,"wordlist":["COVE","PALM","DUNES","CLIFFS","HARBOR","HOTELS","PICNIC","DAYTONA","FISHING","FLORIDA","TOURIST","SWIMMING","RECREATION","DESTINATION"]}