{"id":"12-hard-637","theme":"beach","grid":"DSDRAVELUOBFYWNGEHMIXBXSOIIBOOTGPOJCTMDWCLHHRDGORMAEQAZTQNNAOIAARKCHSAISPNJBTIKOHLHTWGOINFPUONSAERDCFNHSRIILNEIZUZDEEZFUYPKBULSFFILCGCUVGNIDNALG","solution":"68;1;5,66;7;6,108;5;7,29;7;5,131;4;6,115;5;10,142;4;7,118;5;7,107;5;7,85;5;8,76;7;4,105;5;6,97;3;6,10;4;9","gridSize":12,"difficulty":"hard","wordCount":14,"wordlist":["TIDE","OCEAN","SHORE","CLIFFS","HARBOR","INLAND","PICNIC","COASTAL","FISHING","LANDING","NEWPORT","SWIMMING","BOULEVARD","LIGHTHOUSE"]}