{"id":"12-easy-1036","theme":"zeppelin","grid":"KEAYXXUBRBFONIZKMFDEORKEVXOQBJYCRAIDMUMBOILKGMBHBDAOWMAJRIFFPYIXIMNPAGERFLYEEYMIFKURZAPDHKLNUMDOHNUVSUJKISSGTYMRNNKLFIOMQJFRQDOEZGSKOZVXQDIKSQNW","solution":"44;0;4;GMBH,32;0;4;RAID,44;1;4;GRAF,67;0;4;PAGE,56;0;4;RIFF,7;1;4;BECK,67;1;4;PINK,103;0;4;KISS,18;1;5;DYLAN,29;1;5;JIMMY,28;1;5;BOWIE,39;1;5;BOXED","gridSize":12,"difficulty":"easy","wordCount":12,"wordlist":["BECK","GMBH","GRAF","KISS","PAGE","PINK","RAID","RIFF","BOWIE","BOXED","DYLAN","JIMMY"]}