{"id":"12-easy-1119","theme":"giraffe","grid":"TMAKIYOXXZBMORKUDUKHEKFZROCALFADQTUZYAZOOSPPCBCYXNMASAIXRGYMSABLEDSSOBLXRHINOYDGIFCOELANDLHHIHDSNYALASXJSAXIHKFNTGJYHXVQLFAPAOKXWXRMJPBLACEFRYBO","solution":"14;0;4;KUDU,1;0;4;MAKI,13;1;4;ROAN,12;1;4;ORYX,26;0;4;CALF,38;0;4;ZOOS,50;0;5;MASAI,60;0;5;SABLE,72;0;5;RHINO,84;0;5;ELAND,6;1;5;OKAPI,96;0;5;NYALA","gridSize":12,"difficulty":"easy","wordCount":12,"wordlist":["CALF","KUDU","MAKI","ORYX","ROAN","ZOOS","ELAND","MASAI","NYALA","OKAPI","RHINO","SABLE"]}