{"id":"12-easy-1195","theme":"airplane","grid":"NYKGIJQBNGFMDVSVRMORLKNPBRCRASHAEANOYUPFPSLIFTDLKNLLILSGLULVLWAOLIPEENUUQANWOCIAWACIMYENTKNRDDYHUOWINGSWICEMVJLFKDTLHWNOYBPRPBVUFQKJMBJMAWSJVOYF","solution":"44;1;4;FLEW,42;0;4;LIFT,45;1;4;TUNA,55;1;4;GEAR,54;1;4;SPIN,41;1;5;SLICK,40;1;5;PILOT,39;1;5;FLOWN,38;1;5;PLANE,26;0;5;CRASH,98;0;5;WINGS,25;1;6;RUNWAY","gridSize":12,"difficulty":"easy","wordCount":12,"wordlist":["FLEW","GEAR","LIFT","SPIN","TUNA","CRASH","FLOWN","PILOT","PLANE","SLICK","WINGS","RUNWAY"]}