{"id":"12-easy-1487","theme":"tram","grid":"DKQIHKBLAHQEVSHQQXQSMUOXZEGFRWQMSFUZWRDHKFASWTJEAAROUTELVJOGZIIMZCNSNHMEYLOESSZBKYHCFSSTOPSUVQVAACARSIASGQKERNPOLINESPLNEASTOPSSRRXIRAILINEBXTEX","solution":"132;0;4;RAIL,122;0;4;STOP,88;1;4;OSLO,97;0;4;CARS,84;1;4;FARE,135;0;4;LINE,86;0;5;STOPS,63;1;5;METRO,50;0;5;ROUTE,112;0;5;LINES,37;1;5;RAILS,79;1;5;BUSES","gridSize":12,"difficulty":"easy","wordCount":12,"wordlist":["CARS","FARE","LINE","OSLO","RAIL","STOP","BUSES","LINES","METRO","RAILS","ROUTE","STOPS"]}