{"id":"12-easy-1651","theme":"cyclone","grid":"WWOUTFLOWRGDLAWMONSOONBWPQETROUGHAQCDZARAINSUHUXPMKALERTFCHQHUESHEARGIJSTGNXSWINDSAKJTQOTTONGAOWLCYMOFIJIKDZKKDTRACYATFDFAEUMRVRROULWPCTRAWRZHGQ","solution":"101;0;4;FIJI,111;0;5;TRACY,76;1;5;STORM,89;0;5;TONGA,77;0;5;WINDS,63;0;5;SHEAR,51;0;5;ALERT,39;0;5;RAINS,27;0;6;TROUGH,14;1;6;WEAKEN,15;0;7;MONSOON,2;0;7;OUTFLOW","gridSize":12,"difficulty":"easy","wordCount":12,"wordlist":["FIJI","ALERT","RAINS","SHEAR","STORM","TONGA","TRACY","WINDS","TROUGH","WEAKEN","MONSOON","OUTFLOW"]}