{"id":"12-easy-1705","theme":"texture","grid":"ZTASTEEJGARQSDENSEDGESYKOMSFLDEWSVMMFIKMEIDACIVDTLIAASCXTYXMFKNPFHICGGGWHAASPYZIAIJKOFPWMQHUABYXDVIEIIUEBYKMSXXEZMLGZBOCYOETMVCMNGVFEFLOURLQJGJI","solution":"29;1;4;DISH,28;1;4;LEAF,39;1;4;MAPS,26;1;4;SKIN,25;1;4;MILK,12;1;4;SOFT,13;0;5;DENSE,1;0;5;TASTE,75;1;5;SWEET,86;1;5;PIXEL,17;0;5;EDGES,133;0;5;FLOUR","gridSize":12,"difficulty":"easy","wordCount":12,"wordlist":["DISH","LEAF","MAPS","MILK","SKIN","SOFT","DENSE","EDGES","FLOUR","PIXEL","SWEET","TASTE"]}