{"id":"12-easy-176","theme":"exploration","grid":"JZZDMTHGMAXRUJOUIWSEWXNRDWTQNEJZWAWMWQDMELSCXZBLWLBOSLOACJAPMIAOMSLVSNENDVSNLPAETSLXXEIAMARSJJSXJPNSICNGICTESOOANERMBOIPGCAVEFUBETEQLUNARKFXJYHQ","solution":"88;1;4;MINE,121;0;4;CAVE,75;1;4;NASA,39;1;4;MOON,88;0;4;MARS,65;1;5;SPACE,43;1;5;CAVES,50;1;5;BASIN,42;1;5;SOLAR,132;0;5;LUNAR,17;1;5;WELLS,4;1;5;MINES","gridSize":12,"difficulty":"easy","wordCount":12,"wordlist":["CAVE","MARS","MINE","MOON","NASA","BASIN","CAVES","LUNAR","MINES","SOLAR","SPACE","WELLS"]}