{"id":"12-easy-1842","theme":"harbor","grid":"GUAMATOLLDVOYSUNKMANUSYZPIERYACHTZIVMROAHUSJLVBKAPORTOEORNOIREZFQDAWCXPSEATMXJLDENFKMRUCBPSGXRCJALPRZQUVULNSIEXCOJXMYBSCNQKTAFEFSAGCEDPDETBZIACH","solution":"36;1;4;MARE,24;0;4;PIER,13;0;4;SUNK,0;0;4;GUAM,38;0;4;OAHU,49;0;4;PORT,4;0;5;ATOLL,49;1;5;PEARL,84;1;5;MAINE,17;0;5;MANUS,28;0;5;YACHT,42;1;5;SEALS","gridSize":12,"difficulty":"easy","wordCount":12,"wordlist":["GUAM","MARE","OAHU","PIER","PORT","SUNK","ATOLL","MAINE","MANUS","PEARL","SEALS","YACHT"]}