{"id":"12-easy-2148","theme":"irrigation","grid":"CANALHRQKTMTFDRIPXPGZCVXNILEUKCHVOJDPCVMMKHFPRXMARIDPTGUJIPUROSASBATCJEZIPOMOIBRHMCDCWISHCHRCMPDEALQUFDZBKWRFTSOOYLLPOZOFEEPADDYMAKACROPSSRVPMKW","solution":"48;0;4;ARID,37;1;4;CROP,60;1;4;RICE,51;1;4;DAMS,62;1;4;SOIL,24;0;4;NILE,13;0;4;DRIP,0;0;5;CANAL,16;1;5;PUMPS,85;1;5;WATER,132;0;5;CROPS,123;0;5;PADDY","gridSize":12,"difficulty":"easy","wordCount":12,"wordlist":["ARID","CROP","DAMS","DRIP","NILE","RICE","SOIL","CANAL","CROPS","PADDY","PUMPS","WATER"]}