{"id":"12-easy-2273","theme":"glider","grid":"PBQIJTOLQLVBYFPILOTKLJXKJLKNHWYHTSQDAOIFLEWACOSRGWTFKDINPXDCGNESPANGLIDEXWINGSGMAKAJZHXPXHABYZQDWTIFFDOHUZNRQGFFPWQLGCAJQTSCSEFVNMATBCMEFJCVEWTY","solution":"31;1;4;HANG,42;1;4;WING,67;1;4;GMBH,42;0;4;WACO,63;0;4;SPAN,39;0;4;FLEW,26;1;4;KITE,13;1;5;FLOWN,5;1;5;TOWED,14;0;5;PILOT,67;0;5;GLIDE,73;0;5;WINGS","gridSize":12,"difficulty":"easy","wordCount":12,"wordlist":["FLEW","GMBH","HANG","KITE","SPAN","WACO","WING","FLOWN","GLIDE","PILOT","TOWED","WINGS"]}