{"id":"12-easy-2406","theme":"orchestra","grid":"CJAZZREUJPEQOBKPOPSFNAVMBABACHNCTIOUOTOFLUTEKHEOEOPERAHLFQJNHNINTEOLIOFOBRASSKROXAEDUTNGVZNDFPVPVIOLAUSVYBQOGGIAENKYOXRTPWECNQDPKAOUJAYRBFIUHWCL","solution":"1;0;4;JAZZ,12;1;4;OBOE,15;0;4;POPS,26;0;4;BACH,13;1;5;BATON,49;0;5;OPERA,50;1;5;PIANO,39;0;5;FLUTE,72;0;5;BRASS,31;1;5;CELLO,54;1;5;HORNS,96;0;5;VIOLA","gridSize":12,"difficulty":"easy","wordCount":12,"wordlist":["BACH","JAZZ","OBOE","POPS","BATON","BRASS","CELLO","FLUTE","HORNS","OPERA","PIANO","VIOLA"]}