{"id":"12-easy-2427","theme":"helicopter","grid":"FFPILOTZUNAWLFLIESCOHBQTIRRFMWRFDECKGOSMPGALGLPBHKXVNFSEELHLTDIVYLHWAISQLMCFROTORFEJRMEDOWIYGTRPCWHSWNBLWECCRZQYYOFTORNREPXTJMQASIGIWZWEESTLWQRS","solution":"96;1;4;CREW,57;1;4;LIFT,21;1;4;BELL,44;1;4;GEAR,32;0;4;DECK,31;1;4;FLEW,76;0;5;ROTOR,18;1;5;CRASH,53;1;5;FLOWN,2;0;5;PILOT,13;0;5;FLIES,0;1;6;FLIGHT","gridSize":12,"difficulty":"easy","wordCount":12,"wordlist":["BELL","CREW","DECK","FLEW","GEAR","LIFT","CRASH","FLIES","FLOWN","PILOT","ROTOR","FLIGHT"]}