{"id":"12-easy-2798","theme":"sorcerer","grid":"YIDPWINXRJCHBOMZOMAGICGJXDFGBFAIRYQBZNWRICASTSHZCLOAKACHWAUNSPELLROARKXQWFAUSTNNKWREOQMAGEAGTBYKROYQUANAVBYLDYOBHNZLMFFGKKURMNJZWEMQLMJDODYSOKTG","solution":"99;0;4;QUAN,86;0;4;MAGE,41;1;5;CARTE,73;0;5;FAUST,41;0;5;CASTS,60;0;5;SPELL,48;0;5;CLOAK,29;0;5;FAIRY,54;1;5;CONAN,60;1;5;SWORD,17;0;5;MAGIC,43;1;5;SHANG","gridSize":12,"difficulty":"easy","wordCount":12,"wordlist":["MAGE","QUAN","CARTE","CASTS","CLOAK","CONAN","FAIRY","FAUST","MAGIC","SHANG","SPELL","SWORD"]}