{"id":"12-easy-2860","theme":"spectrum","grid":"BHQVNFTVYISDGHCIOWRJVQLMGOHSPCNNPAWFZJHITJSDFJJOPEYBIAIMEIBPEWHLCUGCSXHHAATEATNOAFXQKVLALIALMSVKSEIMVSLOPPYWFSGIAMTRLZSJQQHGNOISENZPJATARIHIZCXP","solution":"86;1;5;LIGHT,61;1;5;WAVES,48;1;5;PEAKS,133;0;5;ATARI,87;1;5;AMIGA,124;0;5;NOISE,67;1;6;COLORS,42;1;6;SIGNAL,53;1;6;AUTISM,68;1;6;SAMPLE,16;1;7;OPTICAL,3;1;7;VISIBLE","gridSize":12,"difficulty":"easy","wordCount":12,"wordlist":["AMIGA","ATARI","LIGHT","NOISE","PEAKS","WAVES","AUTISM","COLORS","SAMPLE","SIGNAL","OPTICAL","VISIBLE"]}