{"id":"12-easy-2924","theme":"temple","grid":"EKFRYYACBFPLJAJAINGQICBCELGBDVBHVVOMSIVAOKTOPZOQOPDBLUAOKEPKJCEAOZIJSHJNMVIBRAMAZAVICKTEDEVINYVUYKYTAMILFDUBVZQHINDUMWVFMLTMAZBXLFCOVVNCRXTAQNSS","solution":"16;1;4;IDOL,27;1;4;BABA,52;1;4;LORD,36;0;4;SIVA,75;1;4;BETH,76;0;4;RAMA,14;0;4;JAIN,1;1;4;KALI,88;0;4;DEVI,111;0;5;HINDU,50;1;5;DEITY,99;0;5;TAMIL","gridSize":12,"difficulty":"easy","wordCount":12,"wordlist":["BABA","BETH","DEVI","IDOL","JAIN","KALI","LORD","RAMA","SIVA","DEITY","HINDU","TAMIL"]}