{"id":"12-easy-3065","theme":"stripes","grid":"MUYPANTSNOUTDBCSINCHUNHLOBLUELJATYXHTTAILOSVIOBJSWFLAGGWEFMNPOIBVODMEXEKARNEFYFCFLNHLNSLIENYIZFNEHMLKHGCITECICOYNIYWRJLIHKKWKOUFEWAFEZUAIBFDNJJR","solution":"50;1;4;FINS,49;1;4;WORN,60;1;4;PALE,50;0;4;FLAG,37;0;4;TAIL,12;1;4;DOTS,25;0;4;BLUE,29;1;4;LOGO,16;0;4;INCH,3;0;5;PANTS,63;1;5;BELLY,7;0;5;SNOUT","gridSize":12,"difficulty":"easy","wordCount":12,"wordlist":["BLUE","DOTS","FINS","FLAG","INCH","LOGO","PALE","TAIL","WORN","BELLY","PANTS","SNOUT"]}