{"id":"12-easy-3212","theme":"vacuum","grid":"GIEBPVYBSIXAAIOSVALVELSSSNPUMPSPSBFVEECJVOLIJWNMSRTORRHSKJLCFTUBEBVTBKSLHPFRBKFOOBYCOULARYWNQSWQSMAKQRGMOYNXEPSEMFYVQPIOHPKKKSAMIMHNHDLANWXIENZR","solution":"73;1;4;PUMP,72;1;4;HOSE,61;0;4;TUBE,50;0;4;TORR,63;1;5;BRAKE,13;1;5;INERT,5;1;5;VAPOR,0;1;5;GASES,26;0;5;PUMPS,16;0;5;VALVE,74;1;5;FLASK,31;1;6;PISTON","gridSize":12,"difficulty":"easy","wordCount":12,"wordlist":["HOSE","PUMP","TORR","TUBE","BRAKE","FLASK","GASES","INERT","PUMPS","VALVE","VAPOR","PISTON"]}