{"id":"12-easy-3215","theme":"animals","grid":"OHPGOATSFIRXVAEMICEVTTFVEYTPREYJCCXIWPSPAFHDKWYLCDCITHCPVMNJADOGSZXCOWPITMWSCINCBKIMSESHEEPTVXBCRAQAATMUXAJFVTUYPXATALKXLIONSQSICHOQDMWPGAYCUTZJ","solution":"61;0;4;DOGS,39;1;4;PIGS,50;1;4;COWS,48;1;4;CATS,28;1;4;RATS,73;1;4;MEAT,27;0;4;PREY,15;0;4;MICE,2;1;4;PETS,3;0;5;GOATS,120;0;5;LIONS,86;0;5;SHEEP","gridSize":12,"difficulty":"easy","wordCount":12,"wordlist":["CATS","COWS","DOGS","MEAT","MICE","PETS","PIGS","PREY","RATS","GOATS","LIONS","SHEEP"]}