{"id":"12-easy-3447","theme":"courage","grid":"GJFLTZHSUCROYIJXFBWBPIQNDYKLRIZHALZDZAEPKFRRSYQXCWHVTADYKUGLKAODXYAEIUTZARNCIETELLCVBDOYRNHDLOLVQBRAVEOUFDISTRUTHMPTADOPNLTXMYEYCSNSIOPWAOBIEVHJ","solution":"94;1;4;LION,93;1;4;ODDS,104;1;4;FACE,91;1;4;DUTY,78;0;4;TELL,90;1;4;HOPE,77;1;5;ENEMY,44;1;5;SKILL,97;0;5;BRAVE,108;0;5;TRUTH,50;1;5;HONOR,37;1;5;AWARD","gridSize":12,"difficulty":"easy","wordCount":12,"wordlist":["DUTY","FACE","HOPE","LION","ODDS","TELL","AWARD","BRAVE","ENEMY","HONOR","SKILL","TRUTH"]}