{"id":"12-easy-481","theme":"fireworks","grid":"BBTHROWNNSWCDANCESCRZOLZFWGRUGJKEREUACFINALELWTJWRADOBEGTMUGKONEYHBYRDSSEWUSXVKKQPVCSDLHFFDKQBCTCSMOKEJRALVQIYBWTALFBEYUSHELLSTYZHEFNLIGHTSIRXAD","solution":"75;1;4;SHOW,97;0;5;SMOKE,89;1;5;FEAST,27;1;5;RIDES,50;0;5;ADOBE,37;1;6;CROWDS,24;1;6;FAWKES,120;0;6;SHELLS,12;0;6;DANCES,133;0;6;LIGHTS,2;0;6;THROWN,38;0;6;FINALE","gridSize":12,"difficulty":"easy","wordCount":12,"wordlist":["SHOW","ADOBE","FEAST","RIDES","SMOKE","CROWDS","DANCES","FAWKES","FINALE","LIGHTS","SHELLS","THROWN"]}