{"id":"12-easy-644","theme":"prophecy","grid":"XZXGIFTBPMLVVRDOOMRWUDQOTRUEWXKQBJGQMBSQVBXXEQHUIISAIAHCWMFJRBQUAMQAMUMIZLWJNPDDDKKZAEQEGIFTSGGUVERSEXJDHSMNVRKULPRPAIWRUMOSESEQLOTYNBWEPFXRLPAA","solution":"3;0;4;GIFT,14;0;4;DOOM,24;0;4;TRUE,37;1;5;BIBLE,96;0;5;VERSE,36;1;5;MIRZA,64;1;5;ANGEL,75;1;5;JESUS,88;0;5;GIFTS,92;1;5;SHALL,121;0;5;MOSES,49;0;6;ISAIAH","gridSize":12,"difficulty":"easy","wordCount":12,"wordlist":["DOOM","GIFT","TRUE","ANGEL","BIBLE","GIFTS","JESUS","MIRZA","MOSES","SHALL","VERSE","ISAIAH"]}